{
    "bankingProducts": [
        {
            "id": "1",
            "name": "Savings Account",
            "description": "Deploy Savings account smart contract to offer secure, long-term savings secured by the Finterent",
            "icon": "current_account_icon",
            "action": {
                "buttonText": "Deploy",
                "navigateTo": "/deploy/1",
                "buttonVariant": "default"
            }
        },
        {
            "id": "2",
            "name": "Fixed Deposit Account Product",
            "description": "Deploy fixed deposit products to offer secure, long-term savings secured by the Finterent",
            "icon": "fixed_deposit_icon",
            "action": {
                "buttonText": "Deploy",
                "navigateTo": "/deploy/2",
                "buttonVariant": "default"
            }
        },
        {
            "id": "3",
            "name": "Current Account Product",
            "description": "Deploy Current account smart contract, secured by the Finterent",
            "icon": "fixed_deposit_icon",
            "action": {
                "buttonText": "Deploy",
                "navigateTo": "/deploy/3",
                "buttonVariant": "default"
            }
        },
        {
            "id": "3",
            "name": "Home Loan Account",
            "description": "Deploy a Home Loan smart contract for your customers on the finternet.",
            "icon": "home_loan_icon",
            "action": {
                "buttonText": "Deploy",
                "navigateTo": "/deploy/3",
                "buttonVariant": "default"
            }
        },
        {
            "id": "4",
            "name": "Car Loan Account",
            "description": "Deploy a Car Loan products for your customers on the finternet.",
            "icon": "car_loan_icon",
            "action": {
                "buttonText": "Deploy",
                "navigateTo": "/deploy/4",
                "buttonVariant": "default"
            }
        },
        {
            "id": "5",
            "name": "Business Loan Account",
            "description": "Deploy a Business loan account for your customers on the finternet.",
            "icon": "business_loan_account_icon",
            "action": {
                "buttonText": "Deploy",
                "navigateTo": "/deploy/5",
                "buttonVariant": "default"
            }
        }
    ],
    "configurations": {
        "currentAccount": {
            "types": [
                {
                    "id": "standard",
                    "name": "Standard Current Account",
                    "selected": true
                },
                {
                    "id": "foreign",
                    "name": "Foreign Currency Current Account",
                    "selected": false
                },
                {
                    "id": "startup",
                    "name": "Startup Current Account",
                    "selected": false
                },
                {
                    "id": "merchant",
                    "name": "Merchant Current Account",
                    "selected": false
                },
                {
                    "id": "special",
                    "name": "Special Current Account",
                    "selected": false
                }
            ],
            "interestRate": {
                "label": "Interest Rate",
                "value": null
            },
            "maximumTransferLimit": {
                "label": "Maximum Transfer Limit over a year",
                "value": null
            },
            "restrictedJurisdictions": {
                "label": "Restricted Jurisdictions",
                "value": null
            }
        }
    }
}